[
  {
    "time": "2026-06-03T19:50:40.096602",
    "msg": "Detected changes in outages_snapshot"
  },
  {
    "time": "2026-06-03T22:30:05.892368",
    "msg": "Detected changes in outages_snapshot"
  },
  {
    "time": "2026-06-04T16:56:12.811235",
    "msg": "Detected changes in outages_snapshot"
  },
  {
    "time": "2026-06-04T20:06:34.257950",
    "msg": "Detected changes in outages_snapshot"
  },
  {
    "time": "2026-06-04T23:10:50.301461",
    "msg": "Detected changes in outages_snapshot"
  },
  {
    "time": "2026-06-05T03:40:13.712652",
    "msg": "Detected changes in outages_snapshot"
  },
  {
    "time": "2026-06-05T15:38:56.831663",
    "msg": "Detected changes in outages_snapshot"
  },
  {
    "time": "2026-06-05T19:31:54.946585",
    "msg": "Detected changes in outages_snapshot"
  },
  {
    "time": "2026-06-06T00:27:37.885842",
    "msg": "Detected changes in outages_snapshot"
  },
  {
    "time": "2026-06-06T02:10:52.415339",
    "msg": "Detected changes in outages_snapshot"
  },
  {
    "time": "2026-06-06T06:01:25.919833",
    "msg": "Detected changes in outages_snapshot"
  },
  {
    "time": "2026-06-06T09:54:40.561229",
    "msg": "Detected changes in outages_snapshot"
  },
  {
    "time": "2026-06-06T13:06:25.629936",
    "msg": "Detected changes in outages_snapshot"
  },
  {
    "time": "2026-06-06T16:43:24.224758",
    "msg": "Detected changes in outages_snapshot"
  },
  {
    "time": "2026-06-06T18:18:01.049065",
    "msg": "Detected changes in outages_snapshot"
  },
  {
    "time": "2026-06-07T00:07:31.894981",
    "msg": "Detected changes in outages_snapshot"
  },
  {
    "time": "2026-06-07T13:31:54.926432",
    "msg": "Detected changes in outages_snapshot"
  },
  {
    "time": "2026-06-07T16:53:36.583027",
    "msg": "Detected changes in outages_snapshot"
  },
  {
    "time": "2026-06-07T18:27:34.189696",
    "msg": "Detected changes in outages_snapshot"
  },
  {
    "time": "2026-06-07T20:18:43.294276",
    "msg": "Detected changes in outages_snapshot"
  },
  {
    "time": "2026-06-07T22:24:08.539292",
    "msg": "Detected changes in outages_snapshot"
  },
  {
    "time": "2026-06-08T00:15:07.183275",
    "msg": "Detected changes in outages_snapshot"
  },
  {
    "time": "2026-06-08T17:09:34.037354",
    "msg": "Detected changes in outages_snapshot"
  },
  {
    "time": "2026-06-08T21:29:25.263018",
    "msg": "Detected changes in outages_snapshot"
  },
  {
    "time": "2026-06-09T00:51:59.067851",
    "msg": "Detected changes in outages_snapshot"
  },
  {
    "time": "2026-06-09T10:48:35.752859",
    "msg": "Detected changes in outages_snapshot"
  },
  {
    "time": "2026-06-09T14:02:18.255737",
    "msg": "Detected changes in outages_snapshot"
  },
  {
    "time": "2026-06-09T17:50:53.584913",
    "msg": "Detected changes in outages_snapshot"
  },
  {
    "time": "2026-06-10T00:48:34.156757",
    "msg": "Detected changes in outages_snapshot"
  },
  {
    "time": "2026-06-10T11:08:54.646091",
    "msg": "Detected changes in outages_snapshot"
  },
  {
    "time": "2026-06-10T15:58:58.333438",
    "msg": "Detected changes in outages_snapshot"
  },
  {
    "time": "2026-06-10T20:00:31.001848",
    "msg": "Detected changes in outages_snapshot"
  },
  {
    "time": "2026-06-10T23:31:49.516187",
    "msg": "Detected changes in outages_snapshot"
  },
  {
    "time": "2026-06-11T02:27:15.903282",
    "msg": "Detected changes in outages_snapshot"
  },
  {
    "time": "2026-06-11T17:01:34.082547",
    "msg": "Detected changes in outages_snapshot"
  },
  {
    "time": "2026-06-11T20:43:06.309979",
    "msg": "Detected changes in outages_snapshot"
  },
  {
    "time": "2026-06-12T02:24:21.637067",
    "msg": "Detected changes in outages_snapshot"
  },
  {
    "time": "2026-06-12T11:27:48.522372",
    "msg": "Detected changes in outages_snapshot"
  },
  {
    "time": "2026-06-12T15:56:48.816406",
    "msg": "Detected changes in outages_snapshot"
  },
  {
    "time": "2026-06-12T16:17:28.732168",
    "msg": "Detected changes in outages_snapshot"
  },
  {
    "time": "2026-06-12T23:12:48.708648",
    "msg": "Detected changes in outages_snapshot"
  },
  {
    "time": "2026-06-13T02:18:56.860763",
    "msg": "Detected changes in outages_snapshot"
  },
  {
    "time": "2026-06-14T00:18:51.881857",
    "msg": "Detected changes in outages_snapshot"
  },
  {
    "time": "2026-06-14T11:20:44.181598",
    "msg": "Detected changes in outages_snapshot"
  },
  {
    "time": "2026-06-14T15:00:47.225279",
    "msg": "Detected changes in outages_snapshot"
  },
  {
    "time": "2026-06-15T00:16:06.809199",
    "msg": "Detected changes in outages_snapshot"
  },
  {
    "time": "2026-06-15T02:12:40.087860",
    "msg": "Detected changes in outages_snapshot"
  },
  {
    "time": "2026-06-15T15:15:17.551268",
    "msg": "Detected changes in outages_snapshot"
  },
  {
    "time": "2026-06-16T01:21:13.670134",
    "msg": "Detected changes in outages_snapshot"
  },
  {
    "time": "2026-06-16T07:01:19.237965",
    "msg": "Detected changes in outages_snapshot"
  },
  {
    "time": "2026-06-16T12:35:06.709447",
    "msg": "Detected changes in outages_snapshot"
  },
  {
    "time": "2026-06-16T18:12:23.411344",
    "msg": "Detected changes in outages_snapshot"
  },
  {
    "time": "2026-06-16T22:38:31.094976",
    "msg": "Detected changes in outages_snapshot"
  },
  {
    "time": "2026-06-17T01:12:48.612849",
    "msg": "Detected changes in outages_snapshot"
  },
  {
    "time": "2026-06-17T12:10:29.559271",
    "msg": "Detected changes in outages_snapshot"
  },
  {
    "time": "2026-06-17T19:57:21.379110",
    "msg": "Detected changes in outages_snapshot"
  },
  {
    "time": "2026-06-18T02:26:43.476652",
    "msg": "Detected changes in outages_snapshot"
  },
  {
    "time": "2026-06-18T06:53:06.883011",
    "msg": "Detected changes in outages_snapshot"
  },
  {
    "time": "2026-06-18T11:49:09.784132",
    "msg": "Detected changes in outages_snapshot"
  },
  {
    "time": "2026-06-18T15:54:06.005858",
    "msg": "Detected changes in outages_snapshot"
  },
  {
    "time": "2026-06-18T16:56:31.569356",
    "msg": "Detected changes in outages_snapshot"
  },
  {
    "time": "2026-06-18T17:52:15.789758",
    "msg": "Detected changes in outages_snapshot"
  },
  {
    "time": "2026-06-18T19:51:45.230963",
    "msg": "Detected changes in outages_snapshot"
  },
  {
    "time": "2026-06-19T02:48:10.368739",
    "msg": "Detected changes in outages_snapshot"
  },
  {
    "time": "2026-06-19T07:13:28.174358",
    "msg": "Detected changes in outages_snapshot"
  },
  {
    "time": "2026-06-19T10:51:18.865497",
    "msg": "Detected changes in outages_snapshot"
  },
  {
    "time": "2026-06-19T11:30:04.819047",
    "msg": "Detected changes in outages_snapshot"
  },
  {
    "time": "2026-06-19T15:44:48.171430",
    "msg": "Detected changes in outages_snapshot"
  },
  {
    "time": "2026-06-19T16:20:58.298683",
    "msg": "Detected changes in outages_snapshot"
  },
  {
    "time": "2026-06-19T18:16:25.537036",
    "msg": "Detected changes in outages_snapshot"
  },
  {
    "time": "2026-06-19T22:54:33.991408",
    "msg": "Detected changes in outages_snapshot"
  },
  {
    "time": "2026-06-20T00:13:43.089790",
    "msg": "Detected changes in outages_snapshot"
  },
  {
    "time": "2026-06-20T10:53:28.447383",
    "msg": "Detected changes in outages_snapshot"
  },
  {
    "time": "2026-06-20T13:35:17.860626",
    "msg": "Detected changes in outages_snapshot"
  },
  {
    "time": "2026-06-20T17:03:58.535837",
    "msg": "Detected changes in outages_snapshot"
  },
  {
    "time": "2026-06-20T20:29:24.114984",
    "msg": "Detected changes in outages_snapshot"
  }
]